fast_dev_cli/__init__.py
fast_dev_cli/__main__.py
fast_dev_cli/cli.py
fast_dev_cli/py.typed
fastdevcli_slim-0.20.1.dist-info/METADATA
fastdevcli_slim-0.20.1.dist-info/WHEEL
fastdevcli_slim-0.20.1.dist-info/entry_points.txt
fastdevcli_slim-0.20.1.dist-info/licenses/LICENSE
tests/__init__.py
tests/assets/uv-tx.lock
tests/assets/uv-upload-time.lock
tests/assets/uv.lock
tests/conftest.py
tests/test_bump.py
tests/test_deps.py
tests/test_exec.py
tests/test_fast_test.py
tests/test_functions.py
tests/test_help.py
tests/test_lint.py
tests/test_poetry_version_plugin.py
tests/test_pypi.py
tests/test_runserver.py
tests/test_sync.py
tests/test_tag.py
tests/test_upgrade.py
tests/test_upload.py
tests/test_version.py
tests/utils.py
fastdevcli_slim-0.20.1.dist-info/RECORD
