Metadata-Version: 2.1
Name: fastdevcli-slim
Version: 0.20.1
Summary: Python project development tool.
Author-Email: Waket Zheng <waketzheng@gmail.com>>
Classifier: Development Status :: 4 - Beta
Classifier: Intended Audience :: Developers
Classifier: Intended Audience :: Science/Research
Classifier: Intended Audience :: System Administrators
Classifier: Operating System :: OS Independent
Classifier: Programming Language :: Python :: 3 :: Only
Classifier: Programming Language :: Python :: 3.10
Classifier: Programming Language :: Python :: 3.11
Classifier: Programming Language :: Python :: 3.12
Classifier: Programming Language :: Python :: 3.13
Classifier: Programming Language :: Python :: 3.14
Classifier: Topic :: Software Development :: Libraries :: Python Modules
Classifier: Topic :: Software Development :: Libraries
Classifier: Topic :: Software Development
Classifier: Typing :: Typed
Classifier: License :: OSI Approved :: MIT License
Project-URL: Homepage, https://github.com/waketzheng/fast-dev-cli
Requires-Python: >=3.10
Requires-Dist: typer-slim<1,>=0.12.3
Requires-Dist: tomli<3,>=2.0.1; python_version < "3.11"
Provides-Extra: standard
Requires-Dist: emoji>=2.12.1; extra == "standard"
Requires-Dist: packaging>=20.5; extra == "standard"
Requires-Dist: coverage>=7.5.1; extra == "standard"
Requires-Dist: pytest>=8.2.0; extra == "standard"
Provides-Extra: all
Requires-Dist: bandit>=1.7.9; extra == "all"
Requires-Dist: pytest-mock>=3.14.0; extra == "all"
Requires-Dist: fast-dev-cli[standard]; extra == "all"
